python_linux_keyutils-0.2.0.dist-info/METADATA
python_linux_keyutils-0.2.0.dist-info/WHEEL
python_linux_keyutils-0.2.0.dist-info/licenses/LICENSE
python_linux_keyutils.libs/libgcc_s-1e52349c.so.1
python_linux_keyutils/__init__.py
python_linux_keyutils/python_linux_keyutils.pypy310-pp73-x86_64-linux-gnu.so
python_linux_keyutils-0.2.0.dist-info/RECORD
