Metadata-Version: 2.4
Name: python-linux-keyutils
Version: 0.2.0
Classifier: Programming Language :: Rust
Classifier: Programming Language :: Python :: Implementation :: CPython
Classifier: Programming Language :: Python :: Implementation :: PyPy
Classifier: Intended Audience :: Developers
Classifier: Operating System :: POSIX :: Linux
License-File: LICENSE
Requires-Python: >=3.8
